<?xml version="1.0" encoding="UTF-8"?>

<root-container name="simple" width="1304" height="489">
  <node name="start" x="52" y="47" width="132" height="36">
    <edge>
      <label x="5" y="-10"/>
    </edge>
  </node>
  <node name="Inicio do Fluxo" x="214" y="202" width="132" height="36">
    <edge>
      <label x="5" y="-10"/>
    </edge>
  </node>
  <node name="Avaliacao pelos Servicos Academicos" x="321" y="92" width="254" height="36">
    <edge>
      <label x="5" y="-10"/>
    </edge>
  </node>
  <node name="Resposta" x="669" y="92" width="132" height="36">
    <edge>
      <label x="5" y="-10"/>
    </edge>
    <edge>
      <label x="5" y="-10"/>
    </edge>
  </node>
  <node name="Avaliacao pela reitoria" x="649" y="223" width="166" height="36">
    <edge>
      <label x="5" y="-10"/>
    </edge>
  </node>
  <node name="Adicionar Documentos" x="392" y="310" width="178" height="36">
    <edge>
      <label x="5" y="-10"/>
    </edge>
    <edge>
      <label x="5" y="-10"/>
    </edge>
  </node>
  <node name="Adicionar Documentos Servicos" x="82" y="308" width="234" height="36">
    <edge>
      <label x="5" y="-10"/>
    </edge>
  </node>
  <node name="Validar Campos" x="911" y="91" width="146" height="36">
    <edge>
      <label x="5" y="-10"/>
    </edge>
  </node>
  <node name="Enviar Mail" x="927" y="321" width="132" height="36">
    <edge>
      <label x="5" y="-10"/>
    </edge>
  </node>
  <node name="Completar Campos" x="908" y="202" width="163" height="36">
    <edge>
      <label x="5" y="-10"/>
    </edge>
  </node>
  <node name="end" x="1171" y="198" width="132" height="36"/>
  <node name="Arquivar Pasta" x="1160" y="314" width="132" height="36">
    <edge>
      <label x="5" y="-10"/>
    </edge>
  </node>
  <node name="decision1" x="45" y="148" width="132" height="36">
    <edge>
      <label x="5" y="-10"/>
    </edge>
    <edge>
      <label x="5" y="-10"/>
    </edge>
  </node>
  <node name="end-state1" x="17" y="236" width="132" height="36"/>
  <deployment graphicalInfoFile="/SIUA/src/main/jpdl/.simple.gpd.xml" imageFile="/SIUA/src/main/jpdl/simple.jpg" serverName="localhost" serverPort="8080" serverDeployer="/OpenKM/workflow-register">
    <classesAndResources>
      <element type="java" value="/SIUA/src/main/java/com/openkm/workflow/action/Transaction1Action.java"/>
      <element type="java" value="/SIUA/src/main/java/com/openkm/workflow/decision/Decision1.java"/>
      <element type="java" value="/SIUA/src/main/java/com/openkm/workflow/decision/Decision2.java"/>
      <element type="java" value="/SIUA/src/main/java/com/openkm/workflow/action/Action2.java"/>
      <element type="java" value="/SIUA/src/main/java/com/openkm/workflow/action/Action3.java"/>
      <element type="java" value="/SIUA/src/main/java/com/openkm/workflow/decision/Comecar.java"/>
    </classesAndResources>
    <additionalFiles>
      <element value="/SIUA/src/main/jpdl/forms.xml"/>
    </additionalFiles>
  </deployment>
</root-container>
